Workbook

Sheet Trade Breakup
A1: Bill Ref. | B1: Description | C1: Quantity | D1: Unit | E1: Rate | F1: Total
B2: GFA
B3: FECA
B4: Ground Floor | C4: =(2759)*(1)*(1)*(1)*(1 + (0)) | D4: m2 | F4: =C4*E4
B5: Level 1 | C5: =(974)*(1)*(1)*(1)*(1 + (0)) | D5: m2 | F5: =C5*E5
B6: UCA
B7: Ground Floor | C7: =(219)*(1)*(1)*(1)*(1 + (0)) | D7: m2 | F7: =C7*E7
B8: Level 1 | C8: =(68)*(1)*(1)*(1)*(1 + (0)) | D8: m2 | F8: =C8*E8
B9: External Area
B10: Ground Floor | C10: =(1896)*(1)*(1)*(1)*(1 + (0)) | D10: m2 | F10: =C10*E10
B11: Demolition
B12: GENERALLY
A13: 1/1A | B13: Tenderers are referred to the Specification for the full particulars of workmanship and materials, and the quantities herein provided shall be read in conjunction with the drawings | D13: Note | F13: =C13*E13
A14: 1/1B | B14: This Builders Bill of Quantities has not been measured in accordance with the Australian Standard Method of Measurement of Building Works, 5th Edition | D14: Note | F14: =C14*E14
A15: 1/1C | B15: The Tenderers should carefully check site to assess the extent of Demolition required for this contract | D15: Note | F15: =C15*E15
B16: REFERENCES
B17: Refer to drawing no. A.058-A for Demolition Plan | D17: Note | F17: =C17*E17
B18: PRICES
B19: Prices shall include for:
A20: 1/1D | B20: Demolition of work | D20: Note | F20: =C20*E20
A21: 1/1E | B21: Taking down, removal and cartage from site | D21: Note | F21: =C21*E21
A22: 1/1F | B22: Cleaning up on completion | D22: Note | F22: =C22*E22
A23: 1/1G | B23: Protecting adjoining surfaces | D23: Note | F23: =C23*E23
A24: 1/1H | B24: Making good to work disturbed | D24: Note | F24: =C24*E24
A25: 1/1J | B25: Recycling waste where required | D25: Note | F25: =C25*E25
A26: 1/1K | B26: Tip fees | D26: Note | F26: =C26*E26
A27: 1/1L | B27: Environmental and sustainable requirements detailed in the specification | D27: Note | F27: =C27*E27
B28: GENERAL ITEMS
A29: 1/1M | B29: Allow for site visit to assess the nature and extent of demolition | C29: =(1)*(1)*(1)*(1)*(1 + (0)) | D29: Item | F29: =C29*E29
A30: D/10A | B30: Allow to remove all vegetation within the demolition zone for the new buildings and associated paths including those not specifically noted on the drawings | C30: =(1)*(1)*(1)*(1)*(1 + (0)) | D30: Item | F30: =C30*E30
A31: 1/1N | B31: Allow to retain and protect existing works / premises on site and adjoining properties | C31: =(1)*(1)*(1)*(1)*(1 + (0)) | D31: Item | F31: =C31*E31
A32: 1/2A | B32: Allow for provision and removal of temporary fencing / screens, hoardings, weather / dust protection measures, security, temporary access, warning notices and the like | C32: =(1)*(1)*(1)*(1)*(1 + (0)) | D32: Item | F32: =C32*E32
A33: 1/2B | B33: Allow for all temporary shoring, propping, supports and the like (other than designed shoring and propping measured following) | C33: =(1)*(1)*(1)*(1)*(1 + (0)) | D33: Item | F33: =C33*E33
A34: 1/2C | B34: Allow for all required credits for recovered materials | C34: =(1)*(1)*(1)*(1)*(1 + (0)) | D34: Item | F34: =C34*E34
A35: 1/2D | B35: Allow for giving notice of any unanticipated hazardous materials or conditions found on site | C35: =(1)*(1)*(1)*(1)*(1 + (0)) | D35: Item | F35: =C35*E35
A36: 1/2E | B36: Allow for giving notice of and providing facilities for inspection | C36: =(1)*(1)*(1)*(1)*(1 + (0)) | D36: Item | F36: =C36*E36
A37: 1/2F | B37: Allow for compliance with quality assurance requirements | C37: =(1)*(1)*(1)*(1)*(1 + (0)) | D37: Item | F37: =C37*E37
A38: 1/2G | B38: Allow for submissions including work plans, data and dilapidation records | C38: =(1)*(1)*(1)*(1)*(1 + (0)) | D38: Item | F38: =C38*E38
A39: 1/2H | B39: Allow for traffic management measures | C39: =(1)*(1)*(1)*(1)*(1 + (0)) | D39: Item | F39: =C39*E39
A40: 1/2J | B40: Allow for all costs associated with meeting local authority requirements and obtaining approvals | C40: =(1)*(1)*(1)*(1)*(1 + (0)) | D40: Item | F40: =C40*E40
... A47: D/10C | B47: Allow to make good all disturbed works | C47: =(1)*(1)*(1)*(1)*(1 + (0)) | D47: Item | F47: =C47*E47
B48: NOTES AND ASSUMPTIONS
A49: D/3H | B49: The following measurement of demolition works are INDICATIVE ONLY and it is the contractors responsibility to inspect the site and establish the full extent of Demolition Works. | D49: Note | F49: =C49*E49
B50: DEMOLITION
B51: Demolish existing pergola | C51: =(30)*(1)*(1)*(1)*(1 + (0)) | D51: m2 | F51: =C51*E51
B52: Demolish existing concrete pad | C52: =(30)*(1)*(1)*(1)*(1 + (0)) | D52: m2 | F52: =C52*E52
B53: SERVICES
A54: D/9A | B54: Allow to remove Electrical Services as required | C54: =(1)*(1)*(1)*(1)*(1 + (0)) | D54: Item | F54: =C54*E54
A55: D/9B | B55: Allow to remove Hydraulic Services as required | C55: =(1)*(1)*(1)*(1)*(1 + (0)) | D55: Item | F55: =C55*E55
A56: D/9C | B56: Allow to remove Mechanical Services as required | C56: =(1)*(1)*(1)*(1)*(1 + (0)) | D56: Item | F56: =C56*E56
B57: Groundworks
B58: GENERALLY
A59: 2/1A | B59: Tenderers are referred to the Specification for the full particulars of workmanship and materials, and the quantities herein provided shall be read in conjunction with the drawings | D59: Note | F59: =C59*E59
A60: 2/1B | B60: This Builders Bill of Quantities has not been measured in accordance with the Australian Standard Method of Measurement of Building Works, 5th Edition | D60: Note | F60: =C60*E60
B61: REFERENCE
B62: Refer to "PSM5181002R REV1" Geotechnical Report for Soil Description at site | D62: Note | F62: =C62*E62
B63: Refer to "88353Cumberland Council_Auburn Basketball CentreV1" for existing ground elevation at site | D63: Note | F63: =C63*E63
B64: Refer to Document "R02RAPAuburn Basketball CentreRev 1" for contamination report | D64: Note | F64: =C64*E64
B65: Refer to following civil drawing series: C102-B for "Sediment and Erosion Control Plan" | D65: Note | F65: =C65*E65
B66: Refer to following structural drawing series: S100 for "General Notes, Footing Plan and Footing & Ground Floor Slab Details" | D66: Note | F66: =C66*E66
B67: PRICES
B68: Prices shall include for:
A69: 2/1C | B69: Getting out, levelling, grading, trimming and forming batters | D69: Note | F69: =C69*E69
A70: 2/1D | B70: Keeping sides plumb and to shape | D70: Note | F70: =C70*E70
A71: 2/1E | B71: Scabbling faces of excavation as required | D71: Note | F71: =C71*E71
A72: 2/1F | B72: Backfilling, ramming solid | D72: Note | F72: =C72*E72
A73: 2/1G | B73: Processing excavated materials suitable for reuse as fill | D73: Note | F73: =C73*E73
A74: 2/1H | B74: Loading and disposal of surplus spoil | D74: Note | F74: =C74*E74
A75: 2/1J | B75: Importing fill where required | D75: Note | F75: =C75*E75
A76: 2/1K | B76: All double handling required | D76: Note | F76: =C76*E76
A77: 2/1L | B77: All costs associated with forming and maintaining stripped material stockpiles | D77: Note | F77: =C77*E77
A78: 2/1M | B78: Tip fees | D78: Note | F78: =C78*E78
A79: 2/1N | B79: The Contractor is deemed to have included for material as found | D79: Note | F79: =C79*E79
B80: GENERAL ITEMS
A81: 2/1P | B81: Allow for giving notice of and providing facilities for inspection | C81: =(1)*(1)*(1)*(1)*(1 + (0)) | D81: Item | F81: =C81*E81
A82: 2/2A | B82: Allow for compliance with quality assurance requirements | C82: =(1)*(1)*(1)*(1)*(1 + (0)) | D82: Item | F82: =C82*E82
A83: 2/2B | B83: Allow for providing samples | C83: =(1)*(1)*(1)*(1)*(1 + (0)) | D83: Item | F83: =C83*E83
A84: 2/2C | B84: Allow for testing | C84: =(1)*(1)*(1)*(1)*(1 + (0)) | D84: Item | F84: =C84*E84
A85: 2/2D | B85: Allow for contractors submissions | C85: =(1)*(1)*(1)*(1)*(1 + (0)) | D85: Item | F85: =C85*E85
A86: 2/2E | B86: Allow for inspection of site | C86: =(1)*(1)*(1)*(1)*(1 + (0)) | D86: Item | F86: =C86*E86
A87: 2/2F | B87: Allow for complying with relevant Acts, By-laws and regulations relating to excavation, planking and strutting | C87: =(1)*(1)*(1)*(1)*(1 + (0)) | D87: Item | F87: =C87*E87
A88: 2/2G | B88: Allow for all costs associated with meeting local authority requirements and obtaining approvals | C88: =(1)*(1)*(1)*(1)*(1 + (0)) | D88: Item | F88: =C88*E88
A89: 2/2H | B89: Allow for locating and marking all existing services including disconnection of redundant services not otherwise allowed for and protection of services to be retained | C89: =(1)*(1)*(1)*(1)*(1 + (0)) | D89: Item | F89: =C89*E89
A90: 2/2J | B90: Allow for a dilapidation survey if required, monitoring of existing buildings, pavements and structures close to work areas, controlling possible damage and making good damage on completion | C90: =(1)*(1)*(1)*(1)*(1 + (0)) | D90: Item | F90: =C90*E90
A91: 2/2K | B91: Allow for keeping excavations free from rain and percolating water by pumping, bailing and other means | C91: =(1)*(1)*(1)*(1)*(1 + (0)) | D91: Item | F91: =C91*E91
A92: 2/2L | B92: Allow for provision and removal of temporary fencing, hoardings warning notices and the like | C92: =(1)*(1)*(1)*(1)*(1 + (0)) | D92: Item | F92: =C92*E92
... A98: 2/3D | B98: Allow for geotechnical investigations, monitoring and reports | C98: =(1)*(1)*(1)*(1)*(1 + (0)) | D98: Item | F98: =C98*E98
B99: NOTES AND ASSUMPTIONS
B100: No working area were considered for detailed excavation | D100: Note | F100: =C100*E100
B101: Contractor to determine suitability of existing soil to be used as fill | D101: Note | F101: =C101*E101
B102: Earthwork quantities have been calculated on AGTEK 3D Software. Refer to images provided for reference. | D102: Note | F102: =C102*E102
B103: SITE CLEARANCE
B104: Removal of Water | C104: =(1)*(1)*(1)*(1)*(1 + (0)) | D104: Item | F104: =C104*E104
B105: Site restoration works to make good areas of site or outside site boundary to existing condition after completion of works if required | C105: =(1)*(1)*(1)*(1)*(1 + (0)) | D105: Item | F105: =C105*E105
B106: Stripping of top soil (100mm)[Area: 5574m2] | C106: =(558)*(1)*(1)*(1)*(1 + (0)) | D106: m3 | F106: =C106*E106
B107: EROSION AND SEDIMENT CONTROL
B108: Sediment Fence composed of 1.5m star pickets at maximum of 2.5m centres, self supporting geotextile and 150x100mm trench with compacted backfill and on rock, set into surface concrete (NB: refer detail to drawing no. C102-B) | C108: =(257)*(1)*(1)*(1)*(1 + (0)) | D108: m | F108: =C108*E108
B109: Drainage swale - 1200mm wide grass lined swale drain with 1%-5% drain gradient (NB: refer detail to drawing no. C102-B) | C109: =(98)*(1)*(1)*(1)*(1 + (0)) | D109: m | F109: =C109*E109
B110: Sandbag Check Dam (NB: refer detail to drawing no. C102-B) | C110: =(7)*(1)*(1)*(1)*(1 + (0)) | D110: no | F110: =C110*E110
B111: Stabilised Temporary Site Access (NB: refer detail to drawing no. C102-B) | C111: =(21)*(1)*(1)*(1)*(1 + (0)) | D111: m2 | F111: =C111*E111
...

Sheet Trade Breakup Showing Markup
A1: Bill Ref. | B1: Description | C1: Quantity | D1: Unit | E1: Rate | F1: Markup | G1: Total
B2: GFA
B3: FECA
B4: Ground Floor | C4: =(2759)*(1)*(1)*(1)*(1 + (0)) | D4: m2 | F4: =(0) | G4: =(C4 * E4 + C4 * E4 * F4)
B5: Level 1 | C5: =(974)*(1)*(1)*(1)*(1 + (0)) | D5: m2 | F5: =(0) | G5: =(C5 * E5 + C5 * E5 * F5)
B6: UCA
B7: Ground Floor | C7: =(219)*(1)*(1)*(1)*(1 + (0)) | D7: m2 | F7: =(0) | G7: =(C7 * E7 + C7 * E7 * F7)
B8: Level 1 | C8: =(68)*(1)*(1)*(1)*(1 + (0)) | D8: m2 | F8: =(0) | G8: =(C8 * E8 + C8 * E8 * F8)
B9: External Area
B10: Ground Floor | C10: =(1896)*(1)*(1)*(1)*(1 + (0)) | D10: m2 | F10: =(0) | G10: =(C10 * E10 + C10 * E10 * F10)
B11: Demolition
B12: GENERALLY
A13: 1/1A | B13: Tenderers are referred to the Specification for the full particulars of workmanship and materials, and the quantities herein provided shall be read in conjunction with the drawings | D13: Note | F13: =(0) | G13: =(C13 * E13 + C13 * E13 * F13)
A14: 1/1B | B14: This Builders Bill of Quantities has not been measured in accordance with the Australian Standard Method of Measurement of Building Works, 5th Edition | D14: Note | F14: =(0) | G14: =(C14 * E14 + C14 * E14 * F14)
A15: 1/1C | B15: The Tenderers should carefully check site to assess the extent of Demolition required for this contract | D15: Note | F15: =(0) | G15: =(C15 * E15 + C15 * E15 * F15)
B16: REFERENCES
B17: Refer to drawing no. A.058-A for Demolition Plan | D17: Note | F17: =(0) | G17: =(C17 * E17 + C17 * E17 * F17)
B18: PRICES
B19: Prices shall include for:
A20: 1/1D | B20: Demolition of work | D20: Note | F20: =(0) | G20: =(C20 * E20 + C20 * E20 * F20)
A21: 1/1E | B21: Taking down, removal and cartage from site | D21: Note | F21: =(0) | G21: =(C21 * E21 + C21 * E21 * F21)
A22: 1/1F | B22: Cleaning up on completion | D22: Note | F22: =(0) | G22: =(C22 * E22 + C22 * E22 * F22)
A23: 1/1G | B23: Protecting adjoining surfaces | D23: Note | F23: =(0) | G23: =(C23 * E23 + C23 * E23 * F23)
A24: 1/1H | B24: Making good to work disturbed | D24: Note | F24: =(0) | G24: =(C24 * E24 + C24 * E24 * F24)
A25: 1/1J | B25: Recycling waste where required | D25: Note | F25: =(0) | G25: =(C25 * E25 + C25 * E25 * F25)
A26: 1/1K | B26: Tip fees | D26: Note | F26: =(0) | G26: =(C26 * E26 + C26 * E26 * F26)
A27: 1/1L | B27: Environmental and sustainable requirements detailed in the specification | D27: Note | F27: =(0) | G27: =(C27 * E27 + C27 * E27 * F27)
B28: GENERAL ITEMS
A29: 1/1M | B29: Allow for site visit to assess the nature and extent of demolition | C29: =(1)*(1)*(1)*(1)*(1 + (0)) | D29: Item | F29: =(0) | G29: =(C29 * E29 + C29 * E29 * F29)
A30: D/10A | B30: Allow to remove all vegetation within the demolition zone for the new buildings and associated paths including those not specifically noted on the drawings | C30: =(1)*(1)*(1)*(1)*(1 + (0)) | D30: Item | F30: =(0) | G30: =(C30 * E30 + C30 * E30 * F30)
A31: 1/1N | B31: Allow to retain and protect existing works / premises on site and adjoining properties | C31: =(1)*(1)*(1)*(1)*(1 + (0)) | D31: Item | F31: =(0) | G31: =(C31 * E31 + C31 * E31 * F31)
A32: 1/2A | B32: Allow for provision and removal of temporary fencing / screens, hoardings, weather / dust protection measures, security, temporary access, warning notices and the like | C32: =(1)*(1)*(1)*(1)*(1 + (0)) | D32: Item | F32: =(0) | G32: =(C32 * E32 + C32 * E32 * F32)
A33: 1/2B | B33: Allow for all temporary shoring, propping, supports and the like (other than designed shoring and propping measured following) | C33: =(1)*(1)*(1)*(1)*(1 + (0)) | D33: Item | F33: =(0) | G33: =(C33 * E33 + C33 * E33 * F33)
A34: 1/2C | B34: Allow for all required credits for recovered materials | C34: =(1)*(1)*(1)*(1)*(1 + (0)) | D34: Item | F34: =(0) | G34: =(C34 * E34 + C34 * E34 * F34)
A35: 1/2D | B35: Allow for giving notice of any unanticipated hazardous materials or conditions found on site | C35: =(1)*(1)*(1)*(1)*(1 + (0)) | D35: Item | F35: =(0) | G35: =(C35 * E35 + C35 * E35 * F35)
A36: 1/2E | B36: Allow for giving notice of and providing facilities for inspection | C36: =(1)*(1)*(1)*(1)*(1 + (0)) | D36: Item | F36: =(0) | G36: =(C36 * E36 + C36 * E36 * F36)
A37: 1/2F | B37: Allow for compliance with quality assurance requirements | C37: =(1)*(1)*(1)*(1)*(1 + (0)) | D37: Item | F37: =(0) | G37: =(C37 * E37 + C37 * E37 * F37)
A38: 1/2G | B38: Allow for submissions including work plans, data and dilapidation records | C38: =(1)*(1)*(1)*(1)*(1 + (0)) | D38: Item | F38: =(0) | G38: =(C38 * E38 + C38 * E38 * F38)
A39: 1/2H | B39: Allow for traffic management measures | C39: =(1)*(1)*(1)*(1)*(1 + (0)) | D39: Item | F39: =(0) | G39: =(C39 * E39 + C39 * E39 * F39)
A40: 1/2J | B40: Allow for all costs associated with meeting local authority requirements and obtaining approvals | C40: =(1)*(1)*(1)*(1)*(1 + (0)) | D40: Item | F40: =(0) | G40: =(C40 * E40 + C40 * E40 * F40)
... A47: D/10C | B47: Allow to make good all disturbed works | C47: =(1)*(1)*(1)*(1)*(1 + (0)) | D47: Item | F47: =(0) | G47: =(C47 * E47 + C47 * E47 * F47)
B48: NOTES AND ASSUMPTIONS
A49: D/3H | B49: The following measurement of demolition works are INDICATIVE ONLY and it is the contractors responsibility to inspect the site and establish the full extent of Demolition Works. | D49: Note | F49: =(0) | G49: =(C49 * E49 + C49 * E49 * F49)
B50: DEMOLITION
B51: Demolish existing pergola | C51: =(30)*(1)*(1)*(1)*(1 + (0)) | D51: m2 | F51: =(0) | G51: =(C51 * E51 + C51 * E51 * F51)
B52: Demolish existing concrete pad | C52: =(30)*(1)*(1)*(1)*(1 + (0)) | D52: m2 | F52: =(0) | G52: =(C52 * E52 + C52 * E52 * F52)
B53: SERVICES
A54: D/9A | B54: Allow to remove Electrical Services as required | C54: =(1)*(1)*(1)*(1)*(1 + (0)) | D54: Item | F54: =(0) | G54: =(C54 * E54 + C54 * E54 * F54)
A55: D/9B | B55: Allow to remove Hydraulic Services as required | C55: =(1)*(1)*(1)*(1)*(1 + (0)) | D55: Item | F55: =(0) | G55: =(C55 * E55 + C55 * E55 * F55)
A56: D/9C | B56: Allow to remove Mechanical Services as required | C56: =(1)*(1)*(1)*(1)*(1 + (0)) | D56: Item | F56: =(0) | G56: =(C56 * E56 + C56 * E56 * F56)
B57: Groundworks
B58: GENERALLY
A59: 2/1A | B59: Tenderers are referred to the Specification for the full particulars of workmanship and materials, and the quantities herein provided shall be read in conjunction with the drawings | D59: Note | F59: =(0) | G59: =(C59 * E59 + C59 * E59 * F59)
A60: 2/1B | B60: This Builders Bill of Quantities has not been measured in accordance with the Australian Standard Method of Measurement of Building Works, 5th Edition | D60: Note | F60: =(0) | G60: =(C60 * E60 + C60 * E60 * F60)
B61: REFERENCE
B62: Refer to "PSM5181002R REV1" Geotechnical Report for Soil Description at site | D62: Note | F62: =(0) | G62: =(C62 * E62 + C62 * E62 * F62)
B63: Refer to "88353Cumberland Council_Auburn Basketball CentreV1" for existing ground elevation at site | D63: Note | F63: =(0) | G63: =(C63 * E63 + C63 * E63 * F63)
B64: Refer to Document "R02RAPAuburn Basketball CentreRev 1" for contamination report | D64: Note | F64: =(0) | G64: =(C64 * E64 + C64 * E64 * F64)
B65: Refer to following civil drawing series: C102-B for "Sediment and Erosion Control Plan" | D65: Note | F65: =(0) | G65: =(C65 * E65 + C65 * E65 * F65)
B66: Refer to following structural drawing series: S100 for "General Notes, Footing Plan and Footing & Ground Floor Slab Details" | D66: Note | F66: =(0) | G66: =(C66 * E66 + C66 * E66 * F66)
B67: PRICES
B68: Prices shall include for:
A69: 2/1C | B69: Getting out, levelling, grading, trimming and forming batters | D69: Note | F69: =(0) | G69: =(C69 * E69 + C69 * E69 * F69)
A70: 2/1D | B70: Keeping sides plumb and to shape | D70: Note | F70: =(0) | G70: =(C70 * E70 + C70 * E70 * F70)
A71: 2/1E | B71: Scabbling faces of excavation as required | D71: Note | F71: =(0) | G71: =(C71 * E71 + C71 * E71 * F71)
A72: 2/1F | B72: Backfilling, ramming solid | D72: Note | F72: =(0) | G72: =(C72 * E72 + C72 * E72 * F72)
A73: 2/1G | B73: Processing excavated materials suitable for reuse as fill | D73: Note | F73: =(0) | G73: =(C73 * E73 + C73 * E73 * F73)
A74: 2/1H | B74: Loading and disposal of surplus spoil | D74: Note | F74: =(0) | G74: =(C74 * E74 + C74 * E74 * F74)
A75: 2/1J | B75: Importing fill where required | D75: Note | F75: =(0) | G75: =(C75 * E75 + C75 * E75 * F75)
A76: 2/1K | B76: All double handling required | D76: Note | F76: =(0) | G76: =(C76 * E76 + C76 * E76 * F76)
A77: 2/1L | B77: All costs associated with forming and maintaining stripped material stockpiles | D77: Note | F77: =(0) | G77: =(C77 * E77 + C77 * E77 * F77)
A78: 2/1M | B78: Tip fees | D78: Note | F78: =(0) | G78: =(C78 * E78 + C78 * E78 * F78)
A79: 2/1N | B79: The Contractor is deemed to have included for material as found | D79: Note | F79: =(0) | G79: =(C79 * E79 + C79 * E79 * F79)
B80: GENERAL ITEMS
A81: 2/1P | B81: Allow for giving notice of and providing facilities for inspection | C81: =(1)*(1)*(1)*(1)*(1 + (0)) | D81: Item | F81: =(0) | G81: =(C81 * E81 + C81 * E81 * F81)
A82: 2/2A | B82: Allow for compliance with quality assurance requirements | C82: =(1)*(1)*(1)*(1)*(1 + (0)) | D82: Item | F82: =(0) | G82: =(C82 * E82 + C82 * E82 * F82)
A83: 2/2B | B83: Allow for providing samples | C83: =(1)*(1)*(1)*(1)*(1 + (0)) | D83: Item | F83: =(0) | G83: =(C83 * E83 + C83 * E83 * F83)
A84: 2/2C | B84: Allow for testing | C84: =(1)*(1)*(1)*(1)*(1 + (0)) | D84: Item | F84: =(0) | G84: =(C84 * E84 + C84 * E84 * F84)
A85: 2/2D | B85: Allow for contractors submissions | C85: =(1)*(1)*(1)*(1)*(1 + (0)) | D85: Item | F85: =(0) | G85: =(C85 * E85 + C85 * E85 * F85)
A86: 2/2E | B86: Allow for inspection of site | C86: =(1)*(1)*(1)*(1)*(1 + (0)) | D86: Item | F86: =(0) | G86: =(C86 * E86 + C86 * E86 * F86)
A87: 2/2F | B87: Allow for complying with relevant Acts, By-laws and regulations relating to excavation, planking and strutting | C87: =(1)*(1)*(1)*(1)*(1 + (0)) | D87: Item | F87: =(0) | G87: =(C87 * E87 + C87 * E87 * F87)
A88: 2/2G | B88: Allow for all costs associated with meeting local authority requirements and obtaining approvals | C88: =(1)*(1)*(1)*(1)*(1 + (0)) | D88: Item | F88: =(0) | G88: =(C88 * E88 + C88 * E88 * F88)
A89: 2/2H | B89: Allow for locating and marking all existing services including disconnection of redundant services not otherwise allowed for and protection of services to be retained | C89: =(1)*(1)*(1)*(1)*(1 + (0)) | D89: Item | F89: =(0) | G89: =(C89 * E89 + C89 * E89 * F89)
A90: 2/2J | B90: Allow for a dilapidation survey if required, monitoring of existing buildings, pavements and structures close to work areas, controlling possible damage and making good damage on completion | C90: =(1)*(1)*(1)*(1)*(1 + (0)) | D90: Item | F90: =(0) | G90: =(C90 * E90 + C90 * E90 * F90)
A91: 2/2K | B91: Allow for keeping excavations free from rain and percolating water by pumping, bailing and other means | C91: =(1)*(1)*(1)*(1)*(1 + (0)) | D91: Item | F91: =(0) | G91: =(C91 * E91 + C91 * E91 * F91)
A92: 2/2L | B92: Allow for provision and removal of temporary fencing, hoardings warning notices and the like | C92: =(1)*(1)*(1)*(1)*(1 + (0)) | D92: Item | F92: =(0) | G92: =(C92 * E92 + C92 * E92 * F92)
... A98: 2/3D | B98: Allow for geotechnical investigations, monitoring and reports | C98: =(1)*(1)*(1)*(1)*(1 + (0)) | D98: Item | F98: =(0) | G98: =(C98 * E98 + C98 * E98 * F98)
B99: NOTES AND ASSUMPTIONS
B100: No working area were considered for detailed excavation | D100: Note | F100: =(0) | G100: =(C100 * E100 + C100 * E100 * F100)
B101: Contractor to determine suitability of existing soil to be used as fill | D101: Note | F101: =(0) | G101: =(C101 * E101 + C101 * E101 * F101)
B102: Earthwork quantities have been calculated on AGTEK 3D Software. Refer to images provided for reference. | D102: Note | F102: =(0) | G102: =(C102 * E102 + C102 * E102 * F102)
B103: SITE CLEARANCE
B104: Removal of Water | C104: =(1)*(1)*(1)*(1)*(1 + (0)) | D104: Item | F104: =(0) | G104: =(C104 * E104 + C104 * E104 * F104)
B105: Site restoration works to make good areas of site or outside site boundary to existing condition after completion of works if required | C105: =(1)*(1)*(1)*(1)*(1 + (0)) | D105: Item | F105: =(0) | G105: =(C105 * E105 + C105 * E105 * F105)
B106: Stripping of top soil (100mm)[Area: 5574m2] | C106: =(558)*(1)*(1)*(1)*(1 + (0)) | D106: m3 | F106: =(0) | G106: =(C106 * E106 + C106 * E106 * F106)
B107: EROSION AND SEDIMENT CONTROL
B108: Sediment Fence composed of 1.5m star pickets at maximum of 2.5m centres, self supporting geotextile and 150x100mm trench with compacted backfill and on rock, set into surface concrete (NB: refer detail to drawing no. C102-B) | C108: =(257)*(1)*(1)*(1)*(1 + (0)) | D108: m | F108: =(0) | G108: =(C108 * E108 + C108 * E108 * F108)
B109: Drainage swale - 1200mm wide grass lined swale drain with 1%-5% drain gradient (NB: refer detail to drawing no. C102-B) | C109: =(98)*(1)*(1)*(1)*(1 + (0)) | D109: m | F109: =(0) | G109: =(C109 * E109 + C109 * E109 * F109)
B110: Sandbag Check Dam (NB: refer detail to drawing no. C102-B) | C110: =(7)*(1)*(1)*(1)*(1 + (0)) | D110: no | F110: =(0) | G110: =(C110 * E110 + C110 * E110 * F110)
B111: Stabilised Temporary Site Access (NB: refer detail to drawing no. C102-B) | C111: =(21)*(1)*(1)*(1)*(1 + (0)) | D111: m2 | F111: =(0) | G111: =(C111 * E111 + C111 * E111 * F111)
...

Sheet Trade Summary
A1: Description | B1: Job % | C1: Cost per Unit | D1: Total
A2: GFA | D2: =SUBTOTAL(9,'Trade Breakup Showing Markup'!G$2:G$10)
A3: Demolition | D3: =SUBTOTAL(9,'Trade Breakup Showing Markup'!G$11:G$56)
A4: Groundworks | D4: =SUBTOTAL(9,'Trade Breakup Showing Markup'!G$57:G$127)
A5: Piling | D5: =SUBTOTAL(9,'Trade Breakup Showing Markup'!G$128:G$157)
A6: Concrete | D6: =SUBTOTAL(9,'Trade Breakup Showing Markup'!G$158:G$304)
A7: Formwork | D7: =SUBTOTAL(9,'Trade Breakup Showing Markup'!G$305:G$429)
A8: Reinforcement | D8: =SUBTOTAL(9,'Trade Breakup Showing Markup'!G$430:G$543)
A9: Precast Concrete | D9: =SUBTOTAL(9,'Trade Breakup Showing Markup'!G$544:G$583)
A10: Structural Steel | D10: =SUBTOTAL(9,'Trade Breakup Showing Markup'!G$584:G$797)
A11: Waterproofing | D11: =SUBTOTAL(9,'Trade Breakup Showing Markup'!G$798:G$852)
A12: Masonry | D12: =SUBTOTAL(9,'Trade Breakup Showing Markup'!G$853:G$1116)
A13: Metalworks | D13: =SUBTOTAL(9,'Trade Breakup Showing Markup'!G$1117:G$1196)
A14: Roofing | D14: =SUBTOTAL(9,'Trade Breakup Showing Markup'!G$1197:G$1263)
A15: Cladding & Louvres | D15: =SUBTOTAL(9,'Trade Breakup Showing Markup'!G$1264:G$1332)
A16: Glazing, Windows & Glazed Doors | D16: =SUBTOTAL(9,'Trade Breakup Showing Markup'!G$1333:G$1441)
A17: Doors and Door Hardware | D17: =SUBTOTAL(9,'Trade Breakup Showing Markup'!G$1442:G$1555)
A18: Partitions & Linings | D18: =SUBTOTAL(9,'Trade Breakup Showing Markup'!G$1556:G$1781)
A19: Ceilings | D19: =SUBTOTAL(9,'Trade Breakup Showing Markup'!G$1782:G$1836)
A20: Carpet | D20: =SUBTOTAL(9,'Trade Breakup Showing Markup'!G$1837:G$1866)
A21: Resilient Finishes | D21: =SUBTOTAL(9,'Trade Breakup Showing Markup'!G$1867:G$1923)
A22: Tiling | D22: =SUBTOTAL(9,'Trade Breakup Showing Markup'!G$1924:G$1967)
A23: Painting | D23: =SUBTOTAL(9,'Trade Breakup Showing Markup'!G$1968:G$2034)
A24: FF&E (Group 1 & 2) | D24: =SUBTOTAL(9,'Trade Breakup Showing Markup'!G$2035:G$2147)
A25: White Goods | D25: =SUBTOTAL(9,'Trade Breakup Showing Markup'!G$2148:G$2186)
A26: Signage | D26: =SUBTOTAL(9,'Trade Breakup Showing Markup'!G$2187:G$2244)
A27: Joinery | D27: =SUBTOTAL(9,'Trade Breakup Showing Markup'!G$2245:G$2300)
A28: Hydraulic Services | D28: =SUBTOTAL(9,'Trade Breakup Showing Markup'!G$2301:G$2326)
A29: Electrical & Security Services | D29: =SUBTOTAL(9,'Trade Breakup Showing Markup'!G$2327:G$2349)
A30: Mechanical Services | D30: =SUBTOTAL(9,'Trade Breakup Showing Markup'!G$2350:G$2368)
A31: Fire Services | D31: =SUBTOTAL(9,'Trade Breakup Showing Markup'!G$2369:G$2389)
A32: Vertical Transport | D32: =SUBTOTAL(9,'Trade Breakup Showing Markup'!G$2390:G$2407)
A33: External Works | D33: =SUBTOTAL(9,'Trade Breakup Showing Markup'!G$2408:G$2533)
A34: External Services | D34: =SUBTOTAL(9,'Trade Breakup Showing Markup'!G$2534:G$2560)
A35: Timber/Wood | D35: =SUBTOTAL(9,'Trade Breakup Showing Markup'!G$2561:G$2589)
A36: Provisional Sums | B36: 100 | D36: =SUBTOTAL(9,'Trade Breakup Showing Markup'!G$2590:G$2593)
D37: =SUBTOTAL(9,'Trade Breakup Showing Markup'!G$2594:G$2594)
A38: Subtotal | D38: ='Trade Breakup Showing Markup'!G2596
A39: Adjustment | D39: ='Trade Breakup Showing Markup'!G2597
A40: G.S.T | D40: ='Trade Breakup Showing Markup'!G2598
A41: Total | D41: ='Trade Breakup Showing Markup'!G2599
